koi_net/__init__.py
koi_net/cache.py
koi_net/core.py
koi_net/effector.py
koi_net/exceptions.py
koi_net/identity.py
koi_net/log_system.py
koi_net/secure_manager.py
koi_net/behaviors/handshaker.py
koi_net/behaviors/profile_monitor.py
koi_net/behaviors/sync_manager.py
koi_net/build/artifact.py
koi_net/build/assembler.py
koi_net/build/comp_order.py
koi_net/build/comp_type.py
koi_net/build/consts.py
koi_net/build/container.py
koi_net/config/core.py
koi_net/config/full_node.py
koi_net/config/loader.py
koi_net/config/partial_node.py
koi_net/config/proxy.py
koi_net/entrypoints/__init__.py
koi_net/entrypoints/base.py
koi_net/entrypoints/poller.py
koi_net/entrypoints/server.py
koi_net/network/__init__.py
koi_net/network/error_handler.py
koi_net/network/event_buffer.py
koi_net/network/event_queue.py
koi_net/network/graph.py
koi_net/network/request_handler.py
koi_net/network/resolver.py
koi_net/network/response_handler.py
koi_net/processor/__init__.py
koi_net/processor/context.py
koi_net/processor/handler.py
koi_net/processor/knowledge_handlers.py
koi_net/processor/knowledge_object.py
koi_net/processor/kobj_queue.py
koi_net/processor/pipeline.py
koi_net/protocol/__init__.py
koi_net/protocol/api_models.py
koi_net/protocol/consts.py
koi_net/protocol/edge.py
koi_net/protocol/envelope.py
koi_net/protocol/errors.py
koi_net/protocol/event.py
koi_net/protocol/model_map.py
koi_net/protocol/node.py
koi_net/protocol/secure.py
koi_net/workers/__init__.py
koi_net/workers/base.py
koi_net/workers/event_worker.py
koi_net/workers/kobj_worker.py
koi_net-1.2.4.dist-info/METADATA
koi_net-1.2.4.dist-info/WHEEL
koi_net-1.2.4.dist-info/licenses/LICENSE
koi_net-1.2.4.dist-info/RECORD
