Metadata-Version: 2.4
Name: koi-net
Version: 1.2.4
Summary: Implementation of KOI-net protocol in Python
Project-URL: Homepage, https://github.com/BlockScience/koi-net/
Author-email: Luke Miller <luke@block.science>
License: MIT License
License-File: LICENSE
Requires-Python: >=3.10
Requires-Dist: cryptography>=45.0.3
Requires-Dist: fastapi>=0.115.12
Requires-Dist: httpx>=0.28.1
Requires-Dist: networkx>=3.4.2
Requires-Dist: pydantic>=2.10.6
Requires-Dist: python-dotenv>=1.1.0
Requires-Dist: rid-lib>=3.2.7
Requires-Dist: ruamel-yaml>=0.18.10
Requires-Dist: structlog>=25.4.0
Requires-Dist: uvicorn>=0.34.2
Provides-Extra: dev
Requires-Dist: build; extra == 'dev'
Requires-Dist: twine>=6.0; extra == 'dev'
Provides-Extra: docs
Requires-Dist: sphinx; extra == 'docs'
Requires-Dist: sphinx-autoapi>=3.6.0; extra == 'docs'
Requires-Dist: sphinx-autodoc-typehints>=3.0.1; extra == 'docs'
Requires-Dist: sphinx-rtd-theme>=3.0.2; extra == 'docs'
